ethpwn/__init__.py
ethpwn/dbg/.gitignore
ethpwn/dbg/TODO.txt
ethpwn/dbg/breakpoint.py
ethpwn/dbg/ethdbg.py
ethpwn/dbg/ethdbg_exceptions.py
ethpwn/dbg/utils.py
ethpwn/ethlib/README.md
ethpwn/ethlib/__init__.py
ethpwn/ethlib/assembly_utils.py
ethpwn/ethlib/contract_labels.py
ethpwn/ethlib/contract_metadata.py
ethpwn/ethlib/contract_registry.py
ethpwn/ethlib/currency_utils.py
ethpwn/ethlib/evm_analyzer.py
ethpwn/ethlib/global_context.py
ethpwn/ethlib/hashes.py
ethpwn/ethlib/prelude.py
ethpwn/ethlib/python_introspection_utils.py
ethpwn/ethlib/serialization_utils.py
ethpwn/ethlib/tokens_utils.py
ethpwn/ethlib/transactions.py
ethpwn/ethlib/user_input.py
ethpwn/ethlib/utils.py
ethpwn/ethlib/cli/__init__.py
ethpwn/ethlib/cli/config.py
ethpwn/ethlib/cli/contract.py
ethpwn/ethlib/cli/credential.py
ethpwn/ethlib/cli/label.py
ethpwn/ethlib/cli/wallet.py
ethpwn/ethlib/compilation/__init__.py
ethpwn/ethlib/compilation/compiler_solidity.py
ethpwn/ethlib/compilation/compiler_vyper.py
ethpwn/ethlib/compilation/srcmap.py
ethpwn/ethlib/compilation/verified_source_code.py
ethpwn/ethlib/config/__init__.py
ethpwn/ethlib/config/credentials.py
ethpwn/ethlib/config/dbg.py
ethpwn/ethlib/config/misc.py
ethpwn/ethlib/config/wallets.py
ethpwn/ethlib/evm/__init__.py
ethpwn/ethlib/evm/analyzer.py
ethpwn/ethlib/evm/txn_condom.py
ethpwn/ethlib/evm/plugins/__init__.py
ethpwn/ethlib/evm/plugins/base.py
ethpwn/ethlib/evm/plugins/opcode_printer.py
ethpwn/ethlib/evm/plugins/sload_tracer.py
ethpwn/ethlib/evm/plugins/sstore_tracer.py
ethpwn/ethlib/evm/plugins/utils.py
ethpwn/ethlib/exploit_templates/Destructible.sol
ethpwn/ethlib/exploit_templates/Targeted.sol
ethpwn/ethlib/exploit_templates/0.6/Destructible.sol
ethpwn/ethlib/exploit_templates/0.6/Targeted.sol
ethpwn/ethlib/token_price_oracle/.gitignore
ethpwn/ethlib/token_price_oracle/__init__.py
ethpwn/ethlib/token_price_oracle/chainlink_eth_pricer.py
ethpwn/ethlib/token_price_oracle/constants.py
ethpwn/ethlib/token_price_oracle/exceptions.py
ethpwn-1.0.0.dist-info/METADATA
ethpwn-1.0.0.dist-info/WHEEL
ethpwn-1.0.0.dist-info/entry_points.txt
ethpwn-1.0.0.dist-info/licenses/LICENSE
ethpwn-1.0.0.dist-info/RECORD
